similarity_ts/__init__.py
similarity_ts/similarity_analysis_computer.py
similarity_ts/similarity_ts.py
similarity_ts/similarity_ts_config.py
similarity_ts/helpers/__init__.py
similarity_ts/helpers/csv_reader_helper.py
similarity_ts/helpers/dynamic_import_helper.py
similarity_ts/helpers/window_sampler.py
similarity_ts/metrics/__init__.py
similarity_ts/metrics/cc.py
similarity_ts/metrics/cp.py
similarity_ts/metrics/dtw.py
similarity_ts/metrics/hi.py
similarity_ts/metrics/js.py
similarity_ts/metrics/kl.py
similarity_ts/metrics/ks.py
similarity_ts/metrics/metric.py
similarity_ts/metrics/metric_computer.py
similarity_ts/metrics/metric_config.py
similarity_ts/metrics/metric_factory.py
similarity_ts/metrics/mmd.py
similarity_ts/plots/__init__.py
similarity_ts/plots/delta.py
similarity_ts/plots/dimensionalty_reduction.py
similarity_ts/plots/dtw.py
similarity_ts/plots/pca.py
similarity_ts/plots/plot.py
similarity_ts/plots/plot_computer.py
similarity_ts/plots/plot_config.py
similarity_ts/plots/plot_factory.py
similarity_ts/plots/tsne.py
similarity_ts/plots/two_dimensions.py
similarity_ts-1.0.6.dist-info/LICENSE
similarity_ts-1.0.6.dist-info/METADATA
similarity_ts-1.0.6.dist-info/WHEEL
similarity_ts-1.0.6.dist-info/top_level.txt
similarity_ts-1.0.6.dist-info/RECORD
