Metadata-Version: 2.1
Name: similarity-ts
Version: 1.0.6
Summary: SimilarityTS is an open-source project designed to facilitate the evaluation and comparison of multivariate time series data
Author-email: Alejandro Fernández-Montes <afdez@us.es>, Damián Fernández-Cerero <damiancerero@us.es>, Felipe Escalera González <fescalera@us.es>
Project-URL: Homepage, https://github.com/alejandrofdez-us/similarity-ts
Project-URL: Bug Tracker, https://github.com/alejandrofdez-us/similarity-ts/issues
Classifier: Programming Language :: Python :: 3
Classifier: License :: OSI Approved :: MIT License
Classifier: Operating System :: OS Independent
Requires-Python: >=3.9
License-File: LICENSE
Requires-Dist: dtaidistance
Requires-Dist: matplotlib
Requires-Dist: pandas
Requires-Dist: scikit-learn
Requires-Dist: tqdm
Requires-Dist: natsort
Requires-Dist: chardet
